{"ENTITY_ID":5,"tables":[{"id":"156dcf22-6539-42ab-ac51-3e76eff40be1","position":{"x":-6,"y":170},"data":{"table_name":"Rates_receipt","fields":[{"fieldName":"score","fieldType":2,"isPK":false,"isNotNull":false,"isUnique":false,"defaultValue":"3","args":"","isAutoIncrement":false}],"next_id":3,"checkName":[],"checkCondition":[]}},{"id":"53a379e9-b9f4-41e9-8e35-9e08af1b8542","position":{"x":435,"y":146},"data":{"table_name":"Receipt","fields":[{"fieldName":"title","fieldType":10,"isPK":true,"isNotNull":false,"isUnique":false,"defaultValue":"","args":["512"],"isAutoIncrement":false},{"fieldName":"content","fieldType":11,"isPK":false,"isNotNull":false,"isUnique":false,"defaultValue":"","args":["512"],"isAutoIncrement":false},{"fieldName":"author","fieldType":10,"isPK":false,"isNotNull":false,"isUnique":false,"defaultValue":"","args":["512"],"isAutoIncrement":false},{"fieldName":"img","fieldType":10,"isPK":false,"isNotNull":false,"isUnique":false,"defaultValue":"","args":["512"],"isAutoIncrement":false},{"fieldName":"ingredients","fieldType":10,"isPK":false,"isNotNull":false,"isUnique":false,"defaultValue":"","args":["512"],"isAutoIncrement":false}],"next_id":5,"checkName":[],"checkCondition":[]}},{"id":"9ff05233-a907-405b-9d2f-c816d9c5ab44","position":{"x":464,"y":358},"data":{"table_name":"Category","fields":[{"fieldName":"name","fieldType":10,"isPK":true,"isNotNull":false,"isUnique":false,"defaultValue":"","args":["512"],"isAutoIncrement":false},{"fieldName":"img","fieldType":10,"isPK":false,"isNotNull":false,"isUnique":false,"defaultValue":"","args":["512"],"isAutoIncrement":false}],"next_id":2,"checkName":[],"checkCondition":[]}},{"id":"c50dc591-25a3-4143-a275-e61436183ccc","position":{"x":-8,"y":358},"data":{"table_name":"Rates_category","fields":[{"fieldName":"score","fieldType":2,"isPK":false,"isNotNull":false,"isUnique":false,"defaultValue":"","args":"","isAutoIncrement":false}],"next_id":1,"checkName":[],"checkCondition":[]}},{"id":"b859ff04-31fb-46c1-9ac8-d9746dab3575","position":{"x":-380,"y":260},"data":{"table_name":"Users","fields":[{"fieldName":"username","fieldType":10,"isPK":true,"isNotNull":false,"isUnique":false,"defaultValue":"","args":["512"],"isAutoIncrement":false},{"fieldName":"email","fieldType":10,"isPK":false,"isNotNull":false,"isUnique":false,"defaultValue":"","args":["512"],"isAutoIncrement":false},{"fieldName":"password","fieldType":10,"isPK":false,"isNotNull":false,"isUnique":false,"defaultValue":"","args":["512"],"isAutoIncrement":false}],"next_id":3,"checkName":[],"checkCondition":[]}}],"links":[{"source":"9ff05233-a907-405b-9d2f-c816d9c5ab44","target":"53a379e9-b9f4-41e9-8e35-9e08af1b8542","order":"normal","sourceCard":"1:1","targetCard":"0:n","label":"new relation","hierType":null,"sourceisweak":false,"targetisweak":false},{"source":"53a379e9-b9f4-41e9-8e35-9e08af1b8542","target":"156dcf22-6539-42ab-ac51-3e76eff40be1","order":"normal","sourceCard":"1:1","targetCard":"0:n","label":"new relation","hierType":null,"sourceisweak":false,"targetisweak":true},{"source":"c50dc591-25a3-4143-a275-e61436183ccc","target":"9ff05233-a907-405b-9d2f-c816d9c5ab44","order":"normal","sourceCard":"0:n","targetCard":"1:1","label":"new relation","hierType":null,"sourceisweak":true,"targetisweak":false},{"source":"b859ff04-31fb-46c1-9ac8-d9746dab3575","target":"156dcf22-6539-42ab-ac51-3e76eff40be1","order":"normal","sourceCard":"1:1","targetCard":"0:n","label":"new relation","hierType":null,"sourceisweak":false,"targetisweak":true},{"source":"b859ff04-31fb-46c1-9ac8-d9746dab3575","target":"c50dc591-25a3-4143-a275-e61436183ccc","order":"normal","sourceCard":"1:1","targetCard":"0:n","label":"new relation","hierType":null,"sourceisweak":false,"targetisweak":true}],"normalization":1,"database":0}